wyn_keras/__init__.py
wyn_keras/densenet.py
wyn_keras/inception.py
wyn_keras/resnet.py
wyn_keras/vgg16.py
wyn_keras/vit.py
wyn_keras-0.2.0.dist-info/METADATA
wyn_keras-0.2.0.dist-info/WHEEL
wyn_keras-0.2.0.dist-info/RECORD
