Metadata-Version: 2.1
Name: wyn-keras
Version: 0.2.0
Summary: Our customized keras package for popular image classifier techniques.
License: MIT
Author: Yiqiao Yin
Author-email: eagle0504@gmail.com
Requires-Python: >=3.10,<4.0
Classifier: License :: OSI Approved :: MIT License
Classifier: Programming Language :: Python :: 3
Classifier: Programming Language :: Python :: 3.10
Classifier: Programming Language :: Python :: 3.11
Classifier: Programming Language :: Python :: 3.12
Requires-Dist: matplotlib (==3.7.1)
Requires-Dist: numpy (==1.25.2)
Requires-Dist: tensorflow (==2.15.0)
Requires-Dist: tensorflow-addons (==0.23.0)
